[
  {
    "type": "mapgen",
    "method": "json",
    "nested_mapgen_id": "mx_decision_tree",
    "object": {
      "mapgensize": [ 24, 24 ],
      "rows": [
        "---Q---Q--  ----Q--Q---Q",
        "-                       ",
        "Q oo  ooo  oooo  o  oo  ",
        "-oo   oo oo oo   oo     ",
        "-  oo  o  oo  oo oooo oo",
        "- o oo      oo oo       ",
        "Q    o   oo   oo  ooo   ",
        "- oooooo    ooooo  oo   ",
        "-o oo     o     oo      ",
        "- o o ooo ooooo ooo oooo",
        "    ooo              oo ",
        "  o     o       oo      ",
        "- o  oooo   X   oo  ooo ",
        "-o   oooo       o ooo   ",
        "Q  oooo                 ",
        "-  ooo  o ooooo ooooo  o",
        "Q  o  oo  ooo   oo      ",
        "- oooooo   ooo    oooo  ",
        "- o  ooo     oooo  oo   ",
        "Q    o    ooo    oooo  o",
        "-oo oo oooo             ",
        "-          ooooo oooooo ",
        "Q  ooo     ooo oo  ooo  ",
        "-  oooo  oo   oo     oo "
      ],
      "flags": [ "ERASE_ALL_BEFORE_PLACING_TERRAIN" ],
      "palettes": [ "backrooms_palette" ],
	  "terrain": { "o": [["t_decision_floor",25],["t_decision_wall",75 ]],
					"X":["t_decision_tree"],
					" ":["t_decision_floor"]}
    }
  },
  {
    "type": "mapgen",
    "method": "json",
    "nested_mapgen_id": "mx_decision_tree_forest",
    "object": {
      "mapgensize": [ 24, 24 ],
      "rows": [
        " oooooo  oooooooo   oooo",
        "oXooo  ooX   ooo   ooooo",
        "o oo  ooo  ooooX o  oo  ",
        " oo X oo oX oo   oo   X ",
        "o  ooX o  oo  ooXoooo oo",
        "o o oo  X   oo oo   X   ",
        "     o   oo  Xoo  ooo   ",
        "o oXooooX   oooooX oo   ",
        " o oo     o     oo      ",
        "o o o Xoo oXooo ooo oXoo",
        "o   ooo  oo   ooo    oo ",
        "  oX    o ooo   oX    X ",
        "o o  ooXo  o    oo  ooo ",
        " o   oooo   Xoo o oXo   ",
        "o  Xooo   oo oo         ",
        " X oooX o XoooX oooooX o",
        "   o  oo  ooo   oX      ",
        "o oooooo   ooo    oooo  ",
        " oo  ooo  X  oXoo  oo   ",
        "  X  o    ooo   Xoooo  o",
        "ooo ooXoooo    X     X  ",
        "ooo        oooXo oooooo ",
        "ooXooo X   ooo oo Xooo  ",
        " oooooo  oo X oo     oo "
      ],
      "flags": [ "ERASE_ALL_BEFORE_PLACING_TERRAIN" ],
      "palettes": [ "backrooms_palette" ],
	  "terrain": { "o": [["t_decision_floor",25],["t_decision_wall",25 ],["t_ink_sh",50]],
					"X":[["t_decision_tree",25],["t_decision_floor",50],["t_ink_sh",25]],
					" ":[["t_decision_floor",50],["t_ink_sh",50]]}
    }
  },
{
    "type": "mapgen",
    "method": "json",
    "nested_mapgen_id": "mx_decision_tree_forest_corner_NE",
	"predecessor_mapgen": "backfloorchamber_north",
    "object": {
      "mapgensize": [ 24, 24 ],
      "rows": [
        " oooooo  oooooooo   oooo",
        "oXooo  ooX   ooo   ooooo",
        "o oo  ooo  ooooX o  oo  ",
        "-oo X oo oX oo   oo   X ",
        "---ooX o  oo  ooXoooo oo",
        "----oo  X   oo oo   X   ",
        "-------  oo  Xoo  ooo   ",
        "--------X   oooooX oo   ",
        "----------o     oo      ",
        "-----------Xooo ooo oXoo",
        "--------------ooo    oo ",
        "-----------------X    X ",
        "--------------------ooo ",
        "---------------------ooo",
        "----------------------oo",
        "-----------------------o",
        "------------------------",
        "------------------------",
        "------------------------",
        "------------------------",
        "------------------------",
        "------------------------",
        "------------------------",
        "------------------------"
      ],
	  "flags":["ALLOW_TERRAIN_UNDER_OTHER_DATA","NO_UNDERLYING_ROTATE"],
      "palettes": [ "backrooms_palette" ],
	  "terrain": { "o": [["t_decision_floor",25],["t_decision_wall",25 ],["t_ink_sh",50]],
					"X":[["t_decision_tree",25],["t_decision_floor",50],["t_ink_sh",25]],
					" ":[["t_decision_floor",50],["t_ink_sh",20]],
					"-":[["t_decision_floor",10],["t_carpet_backrooms",100],["t_ink_sh",5]]}
    }
  },
{
    "type": "mapgen",
    "method": "json",
    "nested_mapgen_id": "mx_decision_tree_forest_corner_NW",
	"predecessor_mapgen": "backfloorchamber_north",
    "object": {
      "mapgensize": [ 24, 24 ],
      "rows": [
        " oooooo  oooooooo   oo--",
        "oXooo  ooX   ooo   oo---",
        "o oo  ooo  ooooX o -----",
        " oo X oo oX oo   oo-----",
        "o  ooX o  oo  ooXoo-----",
        "o o oo  X   oo oo-------",
        "     o   oo  Xoo--------",
        "o oXooooX   oooo--------",
        " o oo     o    ---------",
        "o o o Xoo oXooo---------",
        "o   ooo  oo  -----------",
        "  oX    o ooo-----------",
        "o o  ooXo  o------------",
        " o   oooo  -------------",
        "o  Xooo   oo------------",
        " X oooX o Xo------------",
        "   o  oo----------------",
        "o oooooo----------------",
        " oo  oo-----------------",
        "  X --------------------",
        "ooo---------------------",
        "oo----------------------",
        "o-----------------------",
        "------------------------"
      ],
	  "flags":["ALLOW_TERRAIN_UNDER_OTHER_DATA","NO_UNDERLYING_ROTATE"],
      "palettes": [ "backrooms_palette" ],
	  "terrain": { "o": [["t_decision_floor",25],["t_decision_wall",25 ],["t_ink_sh",50]],
					"X":[["t_decision_tree",25],["t_decision_floor",50],["t_ink_sh",25]],
					" ":[["t_decision_floor",50],["t_ink_sh",20]],
					"-":[["t_decision_floor",10],["t_carpet_backrooms",100],["t_ink_sh",5]]}
    }
  },
  {
    "type": "mapgen",
    "method": "json",
    "nested_mapgen_id": "mx_decision_tree_forest_corner_SW",
	"predecessor_mapgen": "backfloorchamber_north",
    "object": {
      "mapgensize": [ 24, 24 ],
      "rows": [
        "------------------------",
        "o-----------------------",
        "o-----------------------",
        " oo X-------------------",
        "o  ooX------------------",
        "o o oo  X---------------",
        "     o   oo-------------",
        "o oXooooX  -------------",
        " o oo     o ------------",
        "o o o Xoo oXo-----------",
        "o   ooo  oo-------------",
        "  oX    o ooo-----------",
        "o o  ooXo  o------------",
        " o   oooo   Xo----------",
        "o  Xooo   oo oo---------",
        " X oooX o XoooX---------",
        "   o  oo  ooo-----------",
        "o oooooo   ooo----------",
        " oo  ooo  X  oXoo-------",
        "  X  o    ooo   Xo------",
        "ooo ooXoooo    X--------",
        "ooo        oooXo oo-----",
        "ooXooo X   ooo oo Xo----",
        " oooooo  oo X oo -------"
      ],
	  "flags":["ALLOW_TERRAIN_UNDER_OTHER_DATA","NO_UNDERLYING_ROTATE"],
      "palettes": [ "backrooms_palette" ],
	  "terrain": { "o": [["t_decision_floor",25],["t_decision_wall",25 ],["t_ink_sh",50]],
					"X":[["t_decision_tree",25],["t_decision_floor",50],["t_ink_sh",25]],
					" ":[["t_decision_floor",50],["t_ink_sh",20]],
					"-":[["t_decision_floor",10],["t_carpet_backrooms",100],["t_ink_sh",5]]}
    }
  },
{
    "type": "mapgen",
    "method": "json",
    "nested_mapgen_id": "mx_decision_tree_forest_corner_SE",
	"predecessor_mapgen": "backfloorchamber_north",
    "object": {
      "mapgensize": [ 24, 24 ],
      "rows": [
        "--------------------oooo",
        "-------------------ooooo",
        "---------------- o  oo  ",
        "---------------- oo   X ",
        "--------------- Xoooo oo",
        "---------------oo   X   ",
        "---------------o  ooo   ",
        "--------------oooX oo   ",
        "--------------- oo      ",
        "--------------o ooo oXoo",
        "--------------ooo    oo ",
        "----------ooo   oX    X ",
        "--------o  o    oo  ooo ",
        "--------o   Xoo o oXo   ",
        "--------  oo oo         ",
        "------X o XoooX oooooX o",
        "------oo  ooo   oX      ",
        "-------o   ooo    oooo  ",
        "------oo  X  oXoo  oo   ",
        "-----o    ooo   Xoooo  o",
        "-----   ooo    X     X  ",
        "-----      oooXo oooooo ",
        "--Xooo X   ooo oo Xooo  ",
        "--ooooo  oo X oo     oo "
      ],
	  "flags":["ALLOW_TERRAIN_UNDER_OTHER_DATA","NO_UNDERLYING_ROTATE"],
      "palettes": [ "backrooms_palette" ],
	  "terrain": { "o": [["t_decision_floor",25],["t_decision_wall",25 ],["t_ink_sh",50]],
					"X":[["t_decision_tree",25],["t_decision_floor",50],["t_ink_sh",25]],
					" ":[["t_decision_floor",50],["t_ink_sh",20]],
					"-":[["t_decision_floor",10],["t_carpet_backrooms",100],["t_ink_sh",5]]}
    }
  },
  {
    "type": "mapgen",
    "method": "json",
    "nested_mapgen_id": "mx_decision_tree_forest_edge",
	"predecessor_mapgen": "backfloorchamber_north",
    "object": {
      "mapgensize": [ 24, 24 ],
      "rows": [
        " oooooo  oooooooo   oooo",
        "oXooo  ooX   ooo   ooooo",
        "o oo  ooo  ooooX o  oo  ",
        " oo X oo oX oo   oo   X ",
        "o  ooX o  oo  ooXoooo oo",
        "o o oo  X   oo oo   X   ",
        "     o   oo  Xoo  ooo   ",
        "o oXooooX   oooooX oo   ",
        " o oo     o     oo      ",
        "o o o Xoo oXooo ooo oXoo",
        "o   ooo  oo   ooo    oo ",
        "  oX    o ooo   oX    X ",
        "o o  ooXo  o    oo  ooo ",
        " o   oooo   Xoo o oXo   ",
        "o  Xooo   oo oo         ",
        " X oooX o XoooX oooooX o",
        "   o  oo  ooo   oX      ",
        "o oooooo   ooo    oooo  ",
        " oo  ooo  X  oXoo  oo   ",
        "  X  o    ooo   Xoooo  o",
        "ooo ooXoooo    X     X  ",
        "ooo        oooXo oooooo ",
        "ooXooo X   ooo oo Xooo  ",
        " oooooo  oo X oo     oo "
      ],
	  "flags":["ALLOW_TERRAIN_UNDER_OTHER_DATA","NO_UNDERLYING_ROTATE"],
      "palettes": [ "backrooms_palette" ],
	  "terrain": { "o": [["t_decision_floor",25],["t_decision_wall",25 ],["t_ink_sh",50]],
					"X":[["t_decision_tree",25],["t_decision_floor",50],["t_ink_sh",25]],
					" ":[["t_decision_floor",50],["t_ink_sh",20]],
					"-":[["t_decision_floor",10],["t_carpet_backrooms",100],["t_ink_sh",5]]}
    }
  }
]